oncrawl_mcp_server/__init__.py
oncrawl_mcp_server/oncrawl_client.py
oncrawl_mcp_server/server.py
oncrawl_mcp_server-0.4.6.dist-info/METADATA
oncrawl_mcp_server-0.4.6.dist-info/WHEEL
oncrawl_mcp_server-0.4.6.dist-info/entry_points.txt
oncrawl_mcp_server-0.4.6.dist-info/licenses/LICENSE
oncrawl_mcp_server-0.4.6.dist-info/RECORD
