Metadata-Version: 2.4
Name: oncrawl-mcp-server
Version: 0.4.6
Summary: MCP server that exposes OnCrawl's API for use with Claude Code and Claude Desktop
Project-URL: Homepage, https://github.com/Amaculus/oncrawl-mcp-server
Project-URL: Repository, https://github.com/Amaculus/oncrawl-mcp-server
Project-URL: Issues, https://github.com/Amaculus/oncrawl-mcp-server/issues
Project-URL: Documentation, https://github.com/Amaculus/oncrawl-mcp-server#readme
Author: Antonio
License: MIT
License-File: LICENSE
Keywords: api,claude,crawl-analysis,gsc,mcp,oncrawl,seo,technical-seo
Classifier: Development Status :: 4 - Beta
Classifier: Intended Audience :: Developers
Classifier: License :: OSI Approved :: MIT License
Classifier: Programming Language :: Python :: 3
Classifier: Programming Language :: Python :: 3.11
Classifier: Programming Language :: Python :: 3.12
Classifier: Programming Language :: Python :: 3.13
Requires-Python: >=3.11
Requires-Dist: httpx>=0.27.0
Requires-Dist: mcp>=1.0.0
